Workbook

Sheet AAVL 99
A1: AAVL 99 – Market-Cap Weighted Index of 99 stocks (Base 1000 on 25-Sep-2026)
A2: Har trading din ke closing prices us din ke column mein bharein (ya AAVL 99 Terminal ka 'Save closes to Excel' use karein). Index tabhi dikhega jab us din ke saare 99 prices bhare hon.
B4: Base Value | C4: 1000
F6: AAVL 99 Index | G6: =IF(COUNT(G12:G110)<99,"",$C$4*G111/$G$111) -> 1000 | H6: =IF(COUNT(H12:H110)<99,"",$C$4*H111/$G$111) | I6: =IF(COUNT(I12:I110)<99,"",$C$4*I111/$G$111) | J6: =IF(COUNT(J12:J110)<99,"",$C$4*J111/$G$111) | K6: =IF(COUNT(K12:K110)<99,"",$C$4*K111/$G$111) | L6: =IF(COUNT(L12:L110)<99,"",$C$4*L111/$G$111) | M6: =IF(COUNT(M12:M110)<99,"",$C$4*M111/$G$111) | N6: =IF(COUNT(N12:N110)<99,"",$C$4*N111/$G$111) | ... BT6: =IF(COUNT(BT12:BT110)<99,"",$C$4*BT111/$G$111)
F7: Change (pts) | G7: Base | H7: =IF(OR(H6="",G6=""),"",H6-G6) | I7: =IF(OR(I6="",H6=""),"",I6-H6) | J7: =IF(OR(J6="",I6=""),"",J6-I6) | K7: =IF(OR(K6="",J6=""),"",K6-J6) | L7: =IF(OR(L6="",K6=""),"",L6-K6) | M7: =IF(OR(M6="",L6=""),"",M6-L6) | N7: =IF(OR(N6="",M6=""),"",N6-M6) | O7: =IF(OR(O6="",N6=""),"",O6-N6) | ... BT7: =IF(OR(BT6="",BS6=""),"",BT6-BS6)
F8: Change % | G8: Base | H8: =IF(H7="","",H6/G6-1) | I8: =IF(I7="","",I6/H6-1) | J8: =IF(J7="","",J6/I6-1) | K8: =IF(K7="","",K6/J6-1) | L8: =IF(L7="","",L6/K6-1) | M8: =IF(M7="","",M6/L6-1) | N8: =IF(N7="","",N6/M6-1) | O8: =IF(O7="","",O6/N6-1) | ... BT8: =IF(BT7="","",BT6/BS6-1)
F9: Change since base % | G9: =IF(G6="","",G6/$G$6-1) -> 0 | H9: =IF(H6="","",H6/$G$6-1) | I9: =IF(I6="","",I6/$G$6-1) | J9: =IF(J6="","",J6/$G$6-1) | K9: =IF(K6="","",K6/$G$6-1) | L9: =IF(L6="","",L6/$G$6-1) | M9: =IF(M6="","",M6/$G$6-1) | N9: =IF(N6="","",N6/$G$6-1) | ... BT9: =IF(BT6="","",BT6/$G$6-1)
F10: Stocks priced | G10: =COUNT(G12:G110)&"/99" -> 99/99 | H10: =COUNT(H12:H110)&"/99" -> 0/99 | I10: =COUNT(I12:I110)&"/99" -> 0/99 | J10: =COUNT(J12:J110)&"/99" -> 0/99 | K10: =COUNT(K12:K110)&"/99" -> 0/99 | L10: =COUNT(L12:L110)&"/99" -> 0/99 | M10: =COUNT(M12:M110)&"/99" -> 0/99 | N10: =COUNT(N12:N110)&"/99" -> 0/99 | ... BT10: =COUNT(BT12:BT110)&"/99" -> 0/99
A11: # | B11: Company | C11: NSE Symbol | D11: Source MCap (₹ Cr) | E11: Source Price (₹) | F11: Shares (Cr) | G11: 46290 | H11: 46293 | I11: 46294 | J11: 46295 | K11: 46296 | L11: 46300 | M11: 46301 | N11: 46302 | O11: 46303 | P11: 46304 | Q11: 46307 | R11: 46308 | S11: 46309 | T11: 46310 | U11: 46311 | V11: 46314 | W11: 46316 | X11: 46317 | Y11: 46318 | Z11: 46321 | AA11: 46322 | AB11: 46323 | AC11: 46324 | AD11: 46325 | AE11: 46328 | AF11: 46329 | AG11: 46330 | AH11: 46331 | AI11: 46332 | AJ11: 46334 | AK11: 46335 | AL11: 46337 | AM11: 46338 | AN11: 46339 | AO11: 46342 | AP11: 46343 | AQ11: 46344 | AR11: 46345 | AS11: 46346 | AT11: 46349 | AU11: 46351 | AV11: 46352 | AW11: 46353 | AX11: 46356 | AY11: 46357 | AZ11: 46358 | BA11: 46359 | BB11: 46360 | BC11: 46363 | BD11: 46364 | BE11: 46365 | BF11: 46366 | BG11: 46367 | BH11: 46370 | BI11: 46371 | BJ11: 46372 | BK11: 46373 | BL11: 46374 | BM11: 46377 | BN11: 46378 | BO11: 46379 | BP11: 46380 | BQ11: 46384 | BR11: 46385 | BS11: 46386 | BT11: 46387
A12: 1 | B12: Reliance Industries Ltd | C12: RELIANCE | D12: =1353.2*E12 -> 1740891.8 | E12: 1286.5 | F12: =D12/E12 -> 1353.2 | G12: 1286.5
A13: 2 | B13: HDFC Bank Ltd. | C13: HDFCBANK | D13: 1093482 | E13: 715.2 | F13: =D13/E13 -> 1528.9178 | G13: 715.2
A14: 3 | B14: State Bank Of India | C14: SBIN | D14: 946277 | E14: 1042 | F14: =D14/E14 -> 908.13532 | G14: 1042
A15: 4 | B15: ICICI Bank Ltd. | C15: ICICIBANK | D15: 1030255 | E15: 1441 | F15: =D15/E15 -> 714.95836 | G15: 1441
A16: 5 | B16: Tata Consultancy Services Ltd. | C16: TCS | D16: 844253 | E16: 2324.2 | F16: =D16/E16 -> 363.24456 | G16: 2324.2
A17: 6 | B17: Larsen & Toubro Limited | C17: LT | D17: 549301 | E17: 4006 | F17: =D17/E17 -> 137.11957 | G17: 4006
A18: 7 | B18: Infosys Ltd | C18: INFY | D18: 459209 | E18: 1122.9 | F18: =D18/E18 -> 408.94915 | G18: 1122.9
A19: 8 | B19: Hindustan Unilever Ltd. | C19: HINDUNILVR | D19: 461131 | E19: 2005 | F19: =D19/E19 -> 229.99052 | G19: 2005
A20: 9 | B20: Sun Pharmaceutical Industries Ltd. | C20: SUNPHARMA | D20: 459857 | E20: 1919.7 | F20: =D20/E20 -> 239.54628 | G20: 1919.7
A21: 10 | B21: Mahindra & Mahindra Ltd. | C21: M&M | D21: 392769 | E21: 3353 | F21: =D21/E21 -> 117.13958 | G21: 3353
A22: 11 | B22: AXIS Bank Ltd. | C22: AXISBANK | D22: 396207 | E22: 1261.8 | F22: =D22/E22 -> 314.00143 | G22: 1261.8
A23: 12 | B23: ITC Ltd | C23: ITC | D23: 330285 | E23: 264.95 | F23: =D23/E23 -> 1246.5937 | G23: 264.95
A24: 13 | B24: Adani Ports and Special Economic Zone Ltd | C24: ADANIPORTS | D24: 393055 | E24: 1656.8 | F24: =D24/E24 -> 237.23745 | G24: 1656.8
... A110: 99 | B110: SBI Funds Management Ltd | C110: SBIFUNDS | D110: 108186.12 | E110: 531.15 | F110: =D110/E110 -> 203.6828 | G110: 531.15
B111: Total Market Cap (₹ Cr) | G111: =SUMPRODUCT($F$12:$F$110,G12:G110) -> 16836786 | H111: =SUMPRODUCT($F$12:$F$110,H12:H110) -> 0 | I111: =SUMPRODUCT($F$12:$F$110,I12:I110) -> 0 | J111: =SUMPRODUCT($F$12:$F$110,J12:J110) -> 0 | K111: =SUMPRODUCT($F$12:$F$110,K12:K110) -> 0 | L111: =SUMPRODUCT($F$12:$F$110,L12:L110) -> 0 | M111: =SUMPRODUCT($F$12:$F$110,M12:M110) -> 0 | N111: =SUMPRODUCT($F$12:$F$110,N12:N110) -> 0 | ... BT111: =SUMPRODUCT($F$12:$F$110,BT12:BT110) -> 0
A113: Holidays skipped: 2-Oct, 20-Oct, 10-Nov, 24-Nov, 25-Dec-2026 (NSE list). 08-Nov-2026 (Sunday) is Diwali Muhurat trading – fill only if you want to track it.
A114: Shares (Cr) = Source MCap ÷ Source Price from your 'Portfolio Data' sheet. SBI Funds Management: 203.68 Cr shares; source MCap ₹1,08,186.12 Cr on 25-Sep-2026 (ICICI Direct), price derived.

Sheet Stock Daily %
A1: Daily % change of every stock (auto from 'AAVL 99' sheet)
A3: # | B3: Company | C3: NSE Symbol | E3: ='AAVL 99'!G11 -> 46290 | F3: ='AAVL 99'!H11 -> 46293 | G3: ='AAVL 99'!I11 -> 46294 | H3: ='AAVL 99'!J11 -> 46295 | I3: ='AAVL 99'!K11 -> 46296 | J3: ='AAVL 99'!L11 -> 46300 | K3: ='AAVL 99'!M11 -> 46301 | L3: ='AAVL 99'!N11 -> 46302 | ... BR3: ='AAVL 99'!BT11 -> 46387
A4: 1 | B4: ='AAVL 99'!B12 -> Reliance Industries Ltd | C4: ='AAVL 99'!C12 -> RELIANCE | D4: Base | E4: =IF(OR('AAVL 99'!H12="",'AAVL 99'!G12=""),"",'AAVL 99'!H12/'AAVL 99'!G12-1) | F4: =IF(OR('AAVL 99'!I12="",'AAVL 99'!H12=""),"",'AAVL 99'!I12/'AAVL 99'!H12-1) | G4: =IF(OR('AAVL 99'!J12="",'AAVL 99'!I12=""),"",'AAVL 99'!J12/'AAVL 99'!I12-1) | H4: =IF(OR('AAVL 99'!K12="",'AAVL 99'!J12=""),"",'AAVL 99'!K12/'AAVL 99'!J12-1) | I4: =IF(OR('AAVL 99'!L12="",'AAVL 99'!K12=""),"",'AAVL 99'!L12/'AAVL 99'!K12-1) | J4: =IF(OR('AAVL 99'!M12="",'AAVL 99'!L12=""),"",'AAVL 99'!M12/'AAVL 99'!L12-1) | K4: =IF(OR('AAVL 99'!N12="",'AAVL 99'!M12=""),"",'AAVL 99'!N12/'AAVL 99'!M12-1) | L4: =IF(OR('AAVL 99'!O12="",'AAVL 99'!N12=""),"",'AAVL 99'!O12/'AAVL 99'!N12-1) | ... BQ4: =IF(OR('AAVL 99'!BT12="",'AAVL 99'!BS12=""),"",'AAVL 99'!BT12/'AAVL 99'!BS12-1)
A5: 2 | B5: ='AAVL 99'!B13 -> HDFC Bank Ltd. | C5: ='AAVL 99'!C13 -> HDFCBANK | D5: Base | E5: =IF(OR('AAVL 99'!H13="",'AAVL 99'!G13=""),"",'AAVL 99'!H13/'AAVL 99'!G13-1) | F5: =IF(OR('AAVL 99'!I13="",'AAVL 99'!H13=""),"",'AAVL 99'!I13/'AAVL 99'!H13-1) | G5: =IF(OR('AAVL 99'!J13="",'AAVL 99'!I13=""),"",'AAVL 99'!J13/'AAVL 99'!I13-1) | H5: =IF(OR('AAVL 99'!K13="",'AAVL 99'!J13=""),"",'AAVL 99'!K13/'AAVL 99'!J13-1) | I5: =IF(OR('AAVL 99'!L13="",'AAVL 99'!K13=""),"",'AAVL 99'!L13/'AAVL 99'!K13-1) | J5: =IF(OR('AAVL 99'!M13="",'AAVL 99'!L13=""),"",'AAVL 99'!M13/'AAVL 99'!L13-1) | K5: =IF(OR('AAVL 99'!N13="",'AAVL 99'!M13=""),"",'AAVL 99'!N13/'AAVL 99'!M13-1) | L5: =IF(OR('AAVL 99'!O13="",'AAVL 99'!N13=""),"",'AAVL 99'!O13/'AAVL 99'!N13-1) | ... BQ5: =IF(OR('AAVL 99'!BT13="",'AAVL 99'!BS13=""),"",'AAVL 99'!BT13/'AAVL 99'!BS13-1)
A6: 3 | B6: ='AAVL 99'!B14 -> State Bank Of India | C6: ='AAVL 99'!C14 -> SBIN | D6: Base | E6: =IF(OR('AAVL 99'!H14="",'AAVL 99'!G14=""),"",'AAVL 99'!H14/'AAVL 99'!G14-1) | F6: =IF(OR('AAVL 99'!I14="",'AAVL 99'!H14=""),"",'AAVL 99'!I14/'AAVL 99'!H14-1) | G6: =IF(OR('AAVL 99'!J14="",'AAVL 99'!I14=""),"",'AAVL 99'!J14/'AAVL 99'!I14-1) | H6: =IF(OR('AAVL 99'!K14="",'AAVL 99'!J14=""),"",'AAVL 99'!K14/'AAVL 99'!J14-1) | I6: =IF(OR('AAVL 99'!L14="",'AAVL 99'!K14=""),"",'AAVL 99'!L14/'AAVL 99'!K14-1) | J6: =IF(OR('AAVL 99'!M14="",'AAVL 99'!L14=""),"",'AAVL 99'!M14/'AAVL 99'!L14-1) | K6: =IF(OR('AAVL 99'!N14="",'AAVL 99'!M14=""),"",'AAVL 99'!N14/'AAVL 99'!M14-1) | L6: =IF(OR('AAVL 99'!O14="",'AAVL 99'!N14=""),"",'AAVL 99'!O14/'AAVL 99'!N14-1) | ... BQ6: =IF(OR('AAVL 99'!BT14="",'AAVL 99'!BS14=""),"",'AAVL 99'!BT14/'AAVL 99'!BS14-1)
A7: 4 | B7: ='AAVL 99'!B15 -> ICICI Bank Ltd. | C7: ='AAVL 99'!C15 -> ICICIBANK | D7: Base | E7: =IF(OR('AAVL 99'!H15="",'AAVL 99'!G15=""),"",'AAVL 99'!H15/'AAVL 99'!G15-1) | F7: =IF(OR('AAVL 99'!I15="",'AAVL 99'!H15=""),"",'AAVL 99'!I15/'AAVL 99'!H15-1) | G7: =IF(OR('AAVL 99'!J15="",'AAVL 99'!I15=""),"",'AAVL 99'!J15/'AAVL 99'!I15-1) | H7: =IF(OR('AAVL 99'!K15="",'AAVL 99'!J15=""),"",'AAVL 99'!K15/'AAVL 99'!J15-1) | I7: =IF(OR('AAVL 99'!L15="",'AAVL 99'!K15=""),"",'AAVL 99'!L15/'AAVL 99'!K15-1) | J7: =IF(OR('AAVL 99'!M15="",'AAVL 99'!L15=""),"",'AAVL 99'!M15/'AAVL 99'!L15-1) | K7: =IF(OR('AAVL 99'!N15="",'AAVL 99'!M15=""),"",'AAVL 99'!N15/'AAVL 99'!M15-1) | L7: =IF(OR('AAVL 99'!O15="",'AAVL 99'!N15=""),"",'AAVL 99'!O15/'AAVL 99'!N15-1) | ... BQ7: =IF(OR('AAVL 99'!BT15="",'AAVL 99'!BS15=""),"",'AAVL 99'!BT15/'AAVL 99'!BS15-1)
A8: 5 | B8: ='AAVL 99'!B16 -> Tata Consultancy Services Ltd. | C8: ='AAVL 99'!C16 -> TCS | D8: Base | E8: =IF(OR('AAVL 99'!H16="",'AAVL 99'!G16=""),"",'AAVL 99'!H16/'AAVL 99'!G16-1) | F8: =IF(OR('AAVL 99'!I16="",'AAVL 99'!H16=""),"",'AAVL 99'!I16/'AAVL 99'!H16-1) | G8: =IF(OR('AAVL 99'!J16="",'AAVL 99'!I16=""),"",'AAVL 99'!J16/'AAVL 99'!I16-1) | H8: =IF(OR('AAVL 99'!K16="",'AAVL 99'!J16=""),"",'AAVL 99'!K16/'AAVL 99'!J16-1) | I8: =IF(OR('AAVL 99'!L16="",'AAVL 99'!K16=""),"",'AAVL 99'!L16/'AAVL 99'!K16-1) | J8: =IF(OR('AAVL 99'!M16="",'AAVL 99'!L16=""),"",'AAVL 99'!M16/'AAVL 99'!L16-1) | K8: =IF(OR('AAVL 99'!N16="",'AAVL 99'!M16=""),"",'AAVL 99'!N16/'AAVL 99'!M16-1) | L8: =IF(OR('AAVL 99'!O16="",'AAVL 99'!N16=""),"",'AAVL 99'!O16/'AAVL 99'!N16-1) | ... BQ8: =IF(OR('AAVL 99'!BT16="",'AAVL 99'!BS16=""),"",'AAVL 99'!BT16/'AAVL 99'!BS16-1)
A9: 6 | B9: ='AAVL 99'!B17 -> Larsen & Toubro Limited | C9: ='AAVL 99'!C17 -> LT | D9: Base | E9: =IF(OR('AAVL 99'!H17="",'AAVL 99'!G17=""),"",'AAVL 99'!H17/'AAVL 99'!G17-1) | F9: =IF(OR('AAVL 99'!I17="",'AAVL 99'!H17=""),"",'AAVL 99'!I17/'AAVL 99'!H17-1) | G9: =IF(OR('AAVL 99'!J17="",'AAVL 99'!I17=""),"",'AAVL 99'!J17/'AAVL 99'!I17-1) | H9: =IF(OR('AAVL 99'!K17="",'AAVL 99'!J17=""),"",'AAVL 99'!K17/'AAVL 99'!J17-1) | I9: =IF(OR('AAVL 99'!L17="",'AAVL 99'!K17=""),"",'AAVL 99'!L17/'AAVL 99'!K17-1) | J9: =IF(OR('AAVL 99'!M17="",'AAVL 99'!L17=""),"",'AAVL 99'!M17/'AAVL 99'!L17-1) | K9: =IF(OR('AAVL 99'!N17="",'AAVL 99'!M17=""),"",'AAVL 99'!N17/'AAVL 99'!M17-1) | L9: =IF(OR('AAVL 99'!O17="",'AAVL 99'!N17=""),"",'AAVL 99'!O17/'AAVL 99'!N17-1) | ... BQ9: =IF(OR('AAVL 99'!BT17="",'AAVL 99'!BS17=""),"",'AAVL 99'!BT17/'AAVL 99'!BS17-1)
A10: 7 | B10: ='AAVL 99'!B18 -> Infosys Ltd | C10: ='AAVL 99'!C18 -> INFY | D10: Base | E10: =IF(OR('AAVL 99'!H18="",'AAVL 99'!G18=""),"",'AAVL 99'!H18/'AAVL 99'!G18-1) | F10: =IF(OR('AAVL 99'!I18="",'AAVL 99'!H18=""),"",'AAVL 99'!I18/'AAVL 99'!H18-1) | G10: =IF(OR('AAVL 99'!J18="",'AAVL 99'!I18=""),"",'AAVL 99'!J18/'AAVL 99'!I18-1) | H10: =IF(OR('AAVL 99'!K18="",'AAVL 99'!J18=""),"",'AAVL 99'!K18/'AAVL 99'!J18-1) | I10: =IF(OR('AAVL 99'!L18="",'AAVL 99'!K18=""),"",'AAVL 99'!L18/'AAVL 99'!K18-1) | J10: =IF(OR('AAVL 99'!M18="",'AAVL 99'!L18=""),"",'AAVL 99'!M18/'AAVL 99'!L18-1) | K10: =IF(OR('AAVL 99'!N18="",'AAVL 99'!M18=""),"",'AAVL 99'!N18/'AAVL 99'!M18-1) | L10: =IF(OR('AAVL 99'!O18="",'AAVL 99'!N18=""),"",'AAVL 99'!O18/'AAVL 99'!N18-1) | ... BQ10: =IF(OR('AAVL 99'!BT18="",'AAVL 99'!BS18=""),"",'AAVL 99'!BT18/'AAVL 99'!BS18-1)
A11: 8 | B11: ='AAVL 99'!B19 -> Hindustan Unilever Ltd. | C11: ='AAVL 99'!C19 -> HINDUNILVR | D11: Base | E11: =IF(OR('AAVL 99'!H19="",'AAVL 99'!G19=""),"",'AAVL 99'!H19/'AAVL 99'!G19-1) | F11: =IF(OR('AAVL 99'!I19="",'AAVL 99'!H19=""),"",'AAVL 99'!I19/'AAVL 99'!H19-1) | G11: =IF(OR('AAVL 99'!J19="",'AAVL 99'!I19=""),"",'AAVL 99'!J19/'AAVL 99'!I19-1) | H11: =IF(OR('AAVL 99'!K19="",'AAVL 99'!J19=""),"",'AAVL 99'!K19/'AAVL 99'!J19-1) | I11: =IF(OR('AAVL 99'!L19="",'AAVL 99'!K19=""),"",'AAVL 99'!L19/'AAVL 99'!K19-1) | J11: =IF(OR('AAVL 99'!M19="",'AAVL 99'!L19=""),"",'AAVL 99'!M19/'AAVL 99'!L19-1) | K11: =IF(OR('AAVL 99'!N19="",'AAVL 99'!M19=""),"",'AAVL 99'!N19/'AAVL 99'!M19-1) | L11: =IF(OR('AAVL 99'!O19="",'AAVL 99'!N19=""),"",'AAVL 99'!O19/'AAVL 99'!N19-1) | ... BQ11: =IF(OR('AAVL 99'!BT19="",'AAVL 99'!BS19=""),"",'AAVL 99'!BT19/'AAVL 99'!BS19-1)
A12: 9 | B12: ='AAVL 99'!B20 -> Sun Pharmaceutical Industries Ltd. | C12: ='AAVL 99'!C20 -> SUNPHARMA | D12: Base | E12: =IF(OR('AAVL 99'!H20="",'AAVL 99'!G20=""),"",'AAVL 99'!H20/'AAVL 99'!G20-1) | F12: =IF(OR('AAVL 99'!I20="",'AAVL 99'!H20=""),"",'AAVL 99'!I20/'AAVL 99'!H20-1) | G12: =IF(OR('AAVL 99'!J20="",'AAVL 99'!I20=""),"",'AAVL 99'!J20/'AAVL 99'!I20-1) | H12: =IF(OR('AAVL 99'!K20="",'AAVL 99'!J20=""),"",'AAVL 99'!K20/'AAVL 99'!J20-1) | I12: =IF(OR('AAVL 99'!L20="",'AAVL 99'!K20=""),"",'AAVL 99'!L20/'AAVL 99'!K20-1) | J12: =IF(OR('AAVL 99'!M20="",'AAVL 99'!L20=""),"",'AAVL 99'!M20/'AAVL 99'!L20-1) | K12: =IF(OR('AAVL 99'!N20="",'AAVL 99'!M20=""),"",'AAVL 99'!N20/'AAVL 99'!M20-1) | L12: =IF(OR('AAVL 99'!O20="",'AAVL 99'!N20=""),"",'AAVL 99'!O20/'AAVL 99'!N20-1) | ... BQ12: =IF(OR('AAVL 99'!BT20="",'AAVL 99'!BS20=""),"",'AAVL 99'!BT20/'AAVL 99'!BS20-1)
A13: 10 | B13: ='AAVL 99'!B21 -> Mahindra & Mahindra Ltd. | C13: ='AAVL 99'!C21 -> M&M | D13: Base | E13: =IF(OR('AAVL 99'!H21="",'AAVL 99'!G21=""),"",'AAVL 99'!H21/'AAVL 99'!G21-1) | F13: =IF(OR('AAVL 99'!I21="",'AAVL 99'!H21=""),"",'AAVL 99'!I21/'AAVL 99'!H21-1) | G13: =IF(OR('AAVL 99'!J21="",'AAVL 99'!I21=""),"",'AAVL 99'!J21/'AAVL 99'!I21-1) | H13: =IF(OR('AAVL 99'!K21="",'AAVL 99'!J21=""),"",'AAVL 99'!K21/'AAVL 99'!J21-1) | I13: =IF(OR('AAVL 99'!L21="",'AAVL 99'!K21=""),"",'AAVL 99'!L21/'AAVL 99'!K21-1) | J13: =IF(OR('AAVL 99'!M21="",'AAVL 99'!L21=""),"",'AAVL 99'!M21/'AAVL 99'!L21-1) | K13: =IF(OR('AAVL 99'!N21="",'AAVL 99'!M21=""),"",'AAVL 99'!N21/'AAVL 99'!M21-1) | L13: =IF(OR('AAVL 99'!O21="",'AAVL 99'!N21=""),"",'AAVL 99'!O21/'AAVL 99'!N21-1) | ... BQ13: =IF(OR('AAVL 99'!BT21="",'AAVL 99'!BS21=""),"",'AAVL 99'!BT21/'AAVL 99'!BS21-1)
A14: 11 | B14: ='AAVL 99'!B22 -> AXIS Bank Ltd. | C14: ='AAVL 99'!C22 -> AXISBANK | D14: Base | E14: =IF(OR('AAVL 99'!H22="",'AAVL 99'!G22=""),"",'AAVL 99'!H22/'AAVL 99'!G22-1) | F14: =IF(OR('AAVL 99'!I22="",'AAVL 99'!H22=""),"",'AAVL 99'!I22/'AAVL 99'!H22-1) | G14: =IF(OR('AAVL 99'!J22="",'AAVL 99'!I22=""),"",'AAVL 99'!J22/'AAVL 99'!I22-1) | H14: =IF(OR('AAVL 99'!K22="",'AAVL 99'!J22=""),"",'AAVL 99'!K22/'AAVL 99'!J22-1) | I14: =IF(OR('AAVL 99'!L22="",'AAVL 99'!K22=""),"",'AAVL 99'!L22/'AAVL 99'!K22-1) | J14: =IF(OR('AAVL 99'!M22="",'AAVL 99'!L22=""),"",'AAVL 99'!M22/'AAVL 99'!L22-1) | K14: =IF(OR('AAVL 99'!N22="",'AAVL 99'!M22=""),"",'AAVL 99'!N22/'AAVL 99'!M22-1) | L14: =IF(OR('AAVL 99'!O22="",'AAVL 99'!N22=""),"",'AAVL 99'!O22/'AAVL 99'!N22-1) | ... BQ14: =IF(OR('AAVL 99'!BT22="",'AAVL 99'!BS22=""),"",'AAVL 99'!BT22/'AAVL 99'!BS22-1)
A15: 12 | B15: ='AAVL 99'!B23 -> ITC Ltd | C15: ='AAVL 99'!C23 -> ITC | D15: Base | E15: =IF(OR('AAVL 99'!H23="",'AAVL 99'!G23=""),"",'AAVL 99'!H23/'AAVL 99'!G23-1) | F15: =IF(OR('AAVL 99'!I23="",'AAVL 99'!H23=""),"",'AAVL 99'!I23/'AAVL 99'!H23-1) | G15: =IF(OR('AAVL 99'!J23="",'AAVL 99'!I23=""),"",'AAVL 99'!J23/'AAVL 99'!I23-1) | H15: =IF(OR('AAVL 99'!K23="",'AAVL 99'!J23=""),"",'AAVL 99'!K23/'AAVL 99'!J23-1) | I15: =IF(OR('AAVL 99'!L23="",'AAVL 99'!K23=""),"",'AAVL 99'!L23/'AAVL 99'!K23-1) | J15: =IF(OR('AAVL 99'!M23="",'AAVL 99'!L23=""),"",'AAVL 99'!M23/'AAVL 99'!L23-1) | K15: =IF(OR('AAVL 99'!N23="",'AAVL 99'!M23=""),"",'AAVL 99'!N23/'AAVL 99'!M23-1) | L15: =IF(OR('AAVL 99'!O23="",'AAVL 99'!N23=""),"",'AAVL 99'!O23/'AAVL 99'!N23-1) | ... BQ15: =IF(OR('AAVL 99'!BT23="",'AAVL 99'!BS23=""),"",'AAVL 99'!BT23/'AAVL 99'!BS23-1)
... A102: 99 | B102: ='AAVL 99'!B110 -> SBI Funds Management Ltd | C102: ='AAVL 99'!C110 -> SBIFUNDS | D102: Base | E102: =IF(OR('AAVL 99'!H110="",'AAVL 99'!G110=""),"",'AAVL 99'!H110/'AAVL 99'!G110-1) | F102: =IF(OR('AAVL 99'!I110="",'AAVL 99'!H110=""),"",'AAVL 99'!I110/'AAVL 99'!H110-1) | G102: =IF(OR('AAVL 99'!J110="",'AAVL 99'!I110=""),"",'AAVL 99'!J110/'AAVL 99'!I110-1) | H102: =IF(OR('AAVL 99'!K110="",'AAVL 99'!J110=""),"",'AAVL 99'!K110/'AAVL 99'!J110-1) | I102: =IF(OR('AAVL 99'!L110="",'AAVL 99'!K110=""),"",'AAVL 99'!L110/'AAVL 99'!K110-1) | J102: =IF(OR('AAVL 99'!M110="",'AAVL 99'!L110=""),"",'AAVL 99'!M110/'AAVL 99'!L110-1) | K102: =IF(OR('AAVL 99'!N110="",'AAVL 99'!M110=""),"",'AAVL 99'!N110/'AAVL 99'!M110-1) | L102: =IF(OR('AAVL 99'!O110="",'AAVL 99'!N110=""),"",'AAVL 99'!O110/'AAVL 99'!N110-1) | ... BQ102: =IF(OR('AAVL 99'!BT110="",'AAVL 99'!BS110=""),"",'AAVL 99'!BT110/'AAVL 99'!BS110-1)
