Workbook

Sheet Summary
B2: AAVL 99 Replica Portfolio – Summary
B3: Buy every stock in proportion to its market cap, at Friday 25-Sep-2026 prices (same prices as the AAVL 99 index base).
B5: Investment amount (change this) | C5: 38000000 | D5: ← Yellow cell: enter any amount, everything recalculates.
B6: Minimum amount to hold all 99 stocks | C6: =MAX(Portfolio!$P$6:$P$104) -> 37967471
B7: Stock that sets this minimum | C7: =INDEX(Portfolio!$B$6:$B$104,MATCH(C6,Portfolio!$P$6:$P$104,0)) -> Technocraft Industries (India) Ltd.
B8: Total invested | C8: =Portfolio!J105 -> 37853272
B9: Cash left over | C9: =C5-C8 -> 146728
B10: Stocks held (qty ≥ 1) | C10: =COUNTIF(Portfolio!$I$6:$I$104,">=1")&" of 99" -> 99 of 99 | D10: Tracking difference = how far actual weights are from index weights (0% = perfect copy).
B11: Tracking difference vs index weights | C11: =SUMPRODUCT(ABS(Portfolio!$L$6:$L$104))/2 -> 0.0025860135
B12: Portfolio beta (vs Nifty 50) | C12: =IFERROR(SUMPRODUCT(--ISNUMBER(Portfolio!$M$6:$M$104),Portfolio!$K$6:$K$104,Portfolio!$M$6:$M$104)/SUMPRODUCT(--ISNUMBER(Portfolio!$M$6:$M$104),Portfolio!$K$6:$K$104),"Run AAVL99 beta program") -> Run AAVL99 beta program | D12: Beta 1 = moves with Nifty 50. Above 1 = swings more, below 1 = swings less.
B13: Beta coverage (weight of stocks with beta) | C13: =SUMPRODUCT(--ISNUMBER(Portfolio!$M$6:$M$104),Portfolio!$K$6:$K$104) -> 0
B16: Notes
B17: • Prices are the base prices used by the AAVL 99 index (from your Portfolio Data sheet). A few may differ from the official 25-Sep NSE close.
B18: • Quantities are rounded down, so you never spend more than the investment amount; the rest stays as cash.
B19: • Technocraft sets the ₹3.80 Cr minimum because its sheet market cap (₹1,461 Cr) looks too low for its ₹3,295 price. If that figure is wrong, the minimum drops to about ₹1.93 Cr (VST Tillers).
B20: • Beta: 1 year of daily returns (25-Sep-2025 to 25-Sep-2026) vs Nifty 50. Recently listed stocks have fewer days; stocks with under 60 days are left blank.
B21: • Reliance market cap corrected to ~1,353.2 Cr shares × price (source sheet showed 9,115 Cr).

Sheet Sectors
A1: Sector Allocation
A3: Sector | B3: No. of Stocks | C3: Index Weight | D3: Amount Invested (₹) | E3: Portfolio Weight | F3: Sector Beta
A4: Banking | B4: =COUNTIF(Portfolio!$D$6:$D$104,A4) -> 5 | C4: =SUMIF(Portfolio!$D$6:$D$104,A4,Portfolio!$G$6:$G$104) -> 0.21090213 | D4: =SUMIF(Portfolio!$D$6:$D$104,A4,Portfolio!$J$6:$J$104) -> 8011225.2 | E4: =SUMIF(Portfolio!$D$6:$D$104,A4,Portfolio!$K$6:$K$104) -> 0.21163891 | F4: =IFERROR(SUMPRODUCT(--(Portfolio!$D$6:$D$104=A4),--ISNUMBER(Portfolio!$M$6:$M$104),Portfolio!$K$6:$K$104,Portfolio!$M$6:$M$104)/SUMPRODUCT(--(Portfolio!$D$6:$D$104=A4),--ISNUMBER(Portfolio!$M$6:$M$104),Portfolio!$K$6:$K$104),"–") -> –
A5: Oil, Gas & Fuels | B5: =COUNTIF(Portfolio!$D$6:$D$104,A5) -> 4 | C5: =SUMIF(Portfolio!$D$6:$D$104,A5,Portfolio!$G$6:$G$104) -> 0.12218964 | D5: =SUMIF(Portfolio!$D$6:$D$104,A5,Portfolio!$J$6:$J$104) -> 4642610.3 | E5: =SUMIF(Portfolio!$D$6:$D$104,A5,Portfolio!$K$6:$K$104) -> 0.12264753 | F5: =IFERROR(SUMPRODUCT(--(Portfolio!$D$6:$D$104=A5),--ISNUMBER(Portfolio!$M$6:$M$104),Portfolio!$K$6:$K$104,Portfolio!$M$6:$M$104)/SUMPRODUCT(--(Portfolio!$D$6:$D$104=A5),--ISNUMBER(Portfolio!$M$6:$M$104),Portfolio!$K$6:$K$104),"–") -> –
A6: IT | B6: =COUNTIF(Portfolio!$D$6:$D$104,A6) -> 8 | C6: =SUMIF(Portfolio!$D$6:$D$104,A6,Portfolio!$G$6:$G$104) -> 0.10081075 | D6: =SUMIF(Portfolio!$D$6:$D$104,A6,Portfolio!$J$6:$J$104) -> 3821891 | E6: =SUMIF(Portfolio!$D$6:$D$104,A6,Portfolio!$K$6:$K$104) -> 0.10096593 | F6: =IFERROR(SUMPRODUCT(--(Portfolio!$D$6:$D$104=A6),--ISNUMBER(Portfolio!$M$6:$M$104),Portfolio!$K$6:$K$104,Portfolio!$M$6:$M$104)/SUMPRODUCT(--(Portfolio!$D$6:$D$104=A6),--ISNUMBER(Portfolio!$M$6:$M$104),Portfolio!$K$6:$K$104),"–") -> –
A7: Capital Goods & Defence | B7: =COUNTIF(Portfolio!$D$6:$D$104,A7) -> 15 | C7: =SUMIF(Portfolio!$D$6:$D$104,A7,Portfolio!$G$6:$G$104) -> 0.096456296 | D7: =SUMIF(Portfolio!$D$6:$D$104,A7,Portfolio!$J$6:$J$104) -> 3646867.2 | E7: =SUMIF(Portfolio!$D$6:$D$104,A7,Portfolio!$K$6:$K$104) -> 0.096342192 | F7: =IFERROR(SUMPRODUCT(--(Portfolio!$D$6:$D$104=A7),--ISNUMBER(Portfolio!$M$6:$M$104),Portfolio!$K$6:$K$104,Portfolio!$M$6:$M$104)/SUMPRODUCT(--(Portfolio!$D$6:$D$104=A7),--ISNUMBER(Portfolio!$M$6:$M$104),Portfolio!$K$6:$K$104),"–") -> –
A8: FMCG | B8: =COUNTIF(Portfolio!$D$6:$D$104,A8) -> 8 | C8: =SUMIF(Portfolio!$D$6:$D$104,A8,Portfolio!$G$6:$G$104) -> 0.084045138 | D8: =SUMIF(Portfolio!$D$6:$D$104,A8,Portfolio!$J$6:$J$104) -> 3185990.4 | E8: =SUMIF(Portfolio!$D$6:$D$104,A8,Portfolio!$K$6:$K$104) -> 0.084166842 | F8: =IFERROR(SUMPRODUCT(--(Portfolio!$D$6:$D$104=A8),--ISNUMBER(Portfolio!$M$6:$M$104),Portfolio!$K$6:$K$104,Portfolio!$M$6:$M$104)/SUMPRODUCT(--(Portfolio!$D$6:$D$104=A8),--ISNUMBER(Portfolio!$M$6:$M$104),Portfolio!$K$6:$K$104),"–") -> –
A9: Pharma & Healthcare | B9: =COUNTIF(Portfolio!$D$6:$D$104,A9) -> 10 | C9: =SUMIF(Portfolio!$D$6:$D$104,A9,Portfolio!$G$6:$G$104) -> 0.08371972 | D9: =SUMIF(Portfolio!$D$6:$D$104,A9,Portfolio!$J$6:$J$104) -> 3159029.3 | E9: =SUMIF(Portfolio!$D$6:$D$104,A9,Portfolio!$K$6:$K$104) -> 0.08345459 | F9: =IFERROR(SUMPRODUCT(--(Portfolio!$D$6:$D$104=A9),--ISNUMBER(Portfolio!$M$6:$M$104),Portfolio!$K$6:$K$104,Portfolio!$M$6:$M$104)/SUMPRODUCT(--(Portfolio!$D$6:$D$104=A9),--ISNUMBER(Portfolio!$M$6:$M$104),Portfolio!$K$6:$K$104),"–") -> –
A10: Power | B10: =COUNTIF(Portfolio!$D$6:$D$104,A10) -> 6 | C10: =SUMIF(Portfolio!$D$6:$D$104,A10,Portfolio!$G$6:$G$104) -> 0.060036102 | D10: =SUMIF(Portfolio!$D$6:$D$104,A10,Portfolio!$J$6:$J$104) -> 2278948.5 | E10: =SUMIF(Portfolio!$D$6:$D$104,A10,Portfolio!$K$6:$K$104) -> 0.060204796 | F10: =IFERROR(SUMPRODUCT(--(Portfolio!$D$6:$D$104=A10),--ISNUMBER(Portfolio!$M$6:$M$104),Portfolio!$K$6:$K$104,Portfolio!$M$6:$M$104)/SUMPRODUCT(--(Portfolio!$D$6:$D$104=A10),--ISNUMBER(Portfolio!$M$6:$M$104),Portfolio!$K$6:$K$104),"–") -> –
A11: Metals & Mining | B11: =COUNTIF(Portfolio!$D$6:$D$104,A11) -> 6 | C11: =SUMIF(Portfolio!$D$6:$D$104,A11,Portfolio!$G$6:$G$104) -> 0.057043013 | D11: =SUMIF(Portfolio!$D$6:$D$104,A11,Portfolio!$J$6:$J$104) -> 2165856.4 | E11: =SUMIF(Portfolio!$D$6:$D$104,A11,Portfolio!$K$6:$K$104) -> 0.057217152 | F11: =IFERROR(SUMPRODUCT(--(Portfolio!$D$6:$D$104=A11),--ISNUMBER(Portfolio!$M$6:$M$104),Portfolio!$K$6:$K$104,Portfolio!$M$6:$M$104)/SUMPRODUCT(--(Portfolio!$D$6:$D$104=A11),--ISNUMBER(Portfolio!$M$6:$M$104),Portfolio!$K$6:$K$104),"–") -> –
A12: Automobile | B12: =COUNTIF(Portfolio!$D$6:$D$104,A12) -> 9 | C12: =SUMIF(Portfolio!$D$6:$D$104,A12,Portfolio!$G$6:$G$104) -> 0.055594518 | D12: =SUMIF(Portfolio!$D$6:$D$104,A12,Portfolio!$J$6:$J$104) -> 2086983.2 | E12: =SUMIF(Portfolio!$D$6:$D$104,A12,Portfolio!$K$6:$K$104) -> 0.055133497 | F12: =IFERROR(SUMPRODUCT(--(Portfolio!$D$6:$D$104=A12),--ISNUMBER(Portfolio!$M$6:$M$104),Portfolio!$K$6:$K$104,Portfolio!$M$6:$M$104)/SUMPRODUCT(--(Portfolio!$D$6:$D$104=A12),--ISNUMBER(Portfolio!$M$6:$M$104),Portfolio!$K$6:$K$104),"–") -> –
A13: Capital Markets | B13: =COUNTIF(Portfolio!$D$6:$D$104,A13) -> 7 | C13: =SUMIF(Portfolio!$D$6:$D$104,A13,Portfolio!$G$6:$G$104) -> 0.032290077 | D13: =SUMIF(Portfolio!$D$6:$D$104,A13,Portfolio!$J$6:$J$104) -> 1221487.1 | E13: =SUMIF(Portfolio!$D$6:$D$104,A13,Portfolio!$K$6:$K$104) -> 0.032268996 | F13: =IFERROR(SUMPRODUCT(--(Portfolio!$D$6:$D$104=A13),--ISNUMBER(Portfolio!$M$6:$M$104),Portfolio!$K$6:$K$104,Portfolio!$M$6:$M$104)/SUMPRODUCT(--(Portfolio!$D$6:$D$104=A13),--ISNUMBER(Portfolio!$M$6:$M$104),Portfolio!$K$6:$K$104),"–") -> –
A14: Cement | B14: =COUNTIF(Portfolio!$D$6:$D$104,A14) -> 2 | C14: =SUMIF(Portfolio!$D$6:$D$104,A14,Portfolio!$G$6:$G$104) -> 0.025798035 | D14: =SUMIF(Portfolio!$D$6:$D$104,A14,Portfolio!$J$6:$J$104) -> 970910.9 | E14: =SUMIF(Portfolio!$D$6:$D$104,A14,Portfolio!$K$6:$K$104) -> 0.025649326 | F14: =IFERROR(SUMPRODUCT(--(Portfolio!$D$6:$D$104=A14),--ISNUMBER(Portfolio!$M$6:$M$104),Portfolio!$K$6:$K$104,Portfolio!$M$6:$M$104)/SUMPRODUCT(--(Portfolio!$D$6:$D$104=A14),--ISNUMBER(Portfolio!$M$6:$M$104),Portfolio!$K$6:$K$104),"–") -> –
A15: Ports & Services | B15: =COUNTIF(Portfolio!$D$6:$D$104,A15) -> 2 | C15: =SUMIF(Portfolio!$D$6:$D$104,A15,Portfolio!$G$6:$G$104) -> 0.023575402 | D15: =SUMIF(Portfolio!$D$6:$D$104,A15,Portfolio!$J$6:$J$104) -> 894968.95 | E15: =SUMIF(Portfolio!$D$6:$D$104,A15,Portfolio!$K$6:$K$104) -> 0.023643107 | F15: =IFERROR(SUMPRODUCT(--(Portfolio!$D$6:$D$104=A15),--ISNUMBER(Portfolio!$M$6:$M$104),Portfolio!$K$6:$K$104,Portfolio!$M$6:$M$104)/SUMPRODUCT(--(Portfolio!$D$6:$D$104=A15),--ISNUMBER(Portfolio!$M$6:$M$104),Portfolio!$K$6:$K$104),"–") -> –
... A23: Textiles | B23: =COUNTIF(Portfolio!$D$6:$D$104,A23) -> 1 | C23: =SUMIF(Portfolio!$D$6:$D$104,A23,Portfolio!$G$6:$G$104) -> 4.7396219e-05 | D23: =SUMIF(Portfolio!$D$6:$D$104,A23,Portfolio!$J$6:$J$104) -> 1794 | E23: =SUMIF(Portfolio!$D$6:$D$104,A23,Portfolio!$K$6:$K$104) -> 4.7393525e-05 | F23: =IFERROR(SUMPRODUCT(--(Portfolio!$D$6:$D$104=A23),--ISNUMBER(Portfolio!$M$6:$M$104),Portfolio!$K$6:$K$104,Portfolio!$M$6:$M$104)/SUMPRODUCT(--(Portfolio!$D$6:$D$104=A23),--ISNUMBER(Portfolio!$M$6:$M$104),Portfolio!$K$6:$K$104),"–") -> –
A24: TOTAL | B24: =SUM(B4:B23) -> 99 | C24: =SUM(C4:C23) -> 1 | D24: =SUM(D4:D23) -> 37853272 | E24: =SUM(E4:E23) -> 1 | F24: =Summary!C12 -> Run AAVL99 beta program

Sheet Capital Scenarios
A1: How much money do you need?
A2: Same method at different investment amounts. Fewer stocks are held at small amounts because 1 share of a high-price stock costs more than its share of the money.
A4: Investment (₹) | B4: Stocks Held | C4: Amount Invested (₹) | D4: Cash Left (₹) | E4: Tracking Difference
A5: 500000 | B5: =SUMPRODUCT(--(ROUNDDOWN(A5*Portfolio!$G$6:$G$104/Portfolio!$E$6:$E$104,0)>=1)) -> 55 | C5: =SUMPRODUCT(ROUNDDOWN(A5*Portfolio!$G$6:$G$104/Portfolio!$E$6:$E$104,0),Portfolio!$E$6:$E$104) -> 401687.98 | D5: =A5-C5 -> 98312.02 | E5: =SUMPRODUCT(ABS(ROUNDDOWN(A5*Portfolio!$G$6:$G$104/Portfolio!$E$6:$E$104,0)*Portfolio!$E$6:$E$104/C5-Portfolio!$G$6:$G$104))/2 -> 0.15508865
A6: 1000000 | B6: =SUMPRODUCT(--(ROUNDDOWN(A6*Portfolio!$G$6:$G$104/Portfolio!$E$6:$E$104,0)>=1)) -> 76 | C6: =SUMPRODUCT(ROUNDDOWN(A6*Portfolio!$G$6:$G$104/Portfolio!$E$6:$E$104,0),Portfolio!$E$6:$E$104) -> 889601.11 | D6: =A6-C6 -> 110398.89 | E6: =SUMPRODUCT(ABS(ROUNDDOWN(A6*Portfolio!$G$6:$G$104/Portfolio!$E$6:$E$104,0)*Portfolio!$E$6:$E$104/C6-Portfolio!$G$6:$G$104))/2 -> 0.078329229
A7: 2500000 | B7: =SUMPRODUCT(--(ROUNDDOWN(A7*Portfolio!$G$6:$G$104/Portfolio!$E$6:$E$104,0)>=1)) -> 87 | C7: =SUMPRODUCT(ROUNDDOWN(A7*Portfolio!$G$6:$G$104/Portfolio!$E$6:$E$104,0),Portfolio!$E$6:$E$104) -> 2376887.8 | D7: =A7-C7 -> 123112.21 | E7: =SUMPRODUCT(ABS(ROUNDDOWN(A7*Portfolio!$G$6:$G$104/Portfolio!$E$6:$E$104,0)*Portfolio!$E$6:$E$104/C7-Portfolio!$G$6:$G$104))/2 -> 0.03400201
A8: 5000000 | B8: =SUMPRODUCT(--(ROUNDDOWN(A8*Portfolio!$G$6:$G$104/Portfolio!$E$6:$E$104,0)>=1)) -> 94 | C8: =SUMPRODUCT(ROUNDDOWN(A8*Portfolio!$G$6:$G$104/Portfolio!$E$6:$E$104,0),Portfolio!$E$6:$E$104) -> 4858591.9 | D8: =A8-C8 -> 141408.1 | E8: =SUMPRODUCT(ABS(ROUNDDOWN(A8*Portfolio!$G$6:$G$104/Portfolio!$E$6:$E$104,0)*Portfolio!$E$6:$E$104/C8-Portfolio!$G$6:$G$104))/2 -> 0.019006011
A9: 10000000 | B9: =SUMPRODUCT(--(ROUNDDOWN(A9*Portfolio!$G$6:$G$104/Portfolio!$E$6:$E$104,0)>=1)) -> 94 | C9: =SUMPRODUCT(ROUNDDOWN(A9*Portfolio!$G$6:$G$104/Portfolio!$E$6:$E$104,0),Portfolio!$E$6:$E$104) -> 9848908.5 | D9: =A9-C9 -> 151091.48 | E9: =SUMPRODUCT(ABS(ROUNDDOWN(A9*Portfolio!$G$6:$G$104/Portfolio!$E$6:$E$104,0)*Portfolio!$E$6:$E$104/C9-Portfolio!$G$6:$G$104))/2 -> 0.010177046
A10: 20000000 | B10: =SUMPRODUCT(--(ROUNDDOWN(A10*Portfolio!$G$6:$G$104/Portfolio!$E$6:$E$104,0)>=1)) -> 98 | C10: =SUMPRODUCT(ROUNDDOWN(A10*Portfolio!$G$6:$G$104/Portfolio!$E$6:$E$104,0),Portfolio!$E$6:$E$104) -> 19876655 | D10: =A10-C10 -> 123345.24 | E10: =SUMPRODUCT(ABS(ROUNDDOWN(A10*Portfolio!$G$6:$G$104/Portfolio!$E$6:$E$104,0)*Portfolio!$E$6:$E$104/C10-Portfolio!$G$6:$G$104))/2 -> 0.0039388129
A11: =ROUNDUP(Summary!C6,-5) -> 38000000 | B11: =SUMPRODUCT(--(ROUNDDOWN(A11*Portfolio!$G$6:$G$104/Portfolio!$E$6:$E$104,0)>=1)) -> 99 | C11: =SUMPRODUCT(ROUNDDOWN(A11*Portfolio!$G$6:$G$104/Portfolio!$E$6:$E$104,0),Portfolio!$E$6:$E$104) -> 37853272 | D11: =A11-C11 -> 146728 | E11: =SUMPRODUCT(ABS(ROUNDDOWN(A11*Portfolio!$G$6:$G$104/Portfolio!$E$6:$E$104,0)*Portfolio!$E$6:$E$104/C11-Portfolio!$G$6:$G$104))/2 -> 0.0025860135
A12: Last row = minimum for all 99 stocks, rounded up to the next ₹1 lakh. Blue amounts can be changed.

Sheet Portfolio
A1: AAVL 99 Replica Portfolio – bought at 25-Sep-2026 prices
A2: Capital (₹) | C2: =Summary!C5 -> 38000000 | D2: Quantity = ROUNDDOWN(Capital × Weight ÷ Price). Change capital on the Summary sheet. Beta columns fill in when you run the beta program.
A5: # | B5: Company | C5: NSE Symbol | D5: Sector | E5: Price 25-Sep (₹) | F5: Market Cap (₹ Cr) | G5: Target Weight | H5: Target Amount (₹) | I5: Quantity to Buy | J5: Amount Invested (₹) | K5: Actual Weight | L5: Weight Difference | M5: Beta (1Y vs Nifty 50) | N5: Beta Days | O5: Weight × Beta | P5: Capital for 1 Share (₹)
A6: 1 | B6: Reliance Industries Ltd | C6: RELIANCE | D6: Oil, Gas & Fuels | E6: 1286.5 | F6: =1353.2*E6 -> 1740891.8 | G6: =F6/$F$105 -> 0.10339811 | H6: =$C$2*G6 -> 3929128.1 | I6: =ROUNDDOWN(H6/E6,0) -> 3054 | J6: =I6*E6 -> 3928971 | K6: =IF($J$105=0,0,J6/$J$105) -> 0.10379475 | L6: =K6-G6 -> 0.00039664507 | O6: =IF(ISNUMBER(M6),K6*M6,"") | P6: =E6/G6 -> 12442.201
A7: 2 | B7: HDFC Bank Ltd. | C7: HDFCBANK | D7: Banking | E7: 715.2 | F7: 1093482 | G7: =F7/$F$105 -> 0.064946006 | H7: =$C$2*G7 -> 2467948.2 | I7: =ROUNDDOWN(H7/E7,0) -> 3450 | J7: =I7*E7 -> 2467440 | K7: =IF($J$105=0,0,J7/$J$105) -> 0.065184325 | L7: =K7-G7 -> 0.00023831938 | O7: =IF(ISNUMBER(M7),K7*M7,"") | P7: =E7/G7 -> 11012.225
A8: 3 | B8: State Bank Of India | C8: SBIN | D8: Banking | E8: 1042 | F8: 946277 | G8: =F8/$F$105 -> 0.056202948 | H8: =$C$2*G8 -> 2135712 | I8: =ROUNDDOWN(H8/E8,0) -> 2049 | J8: =I8*E8 -> 2135058 | K8: =IF($J$105=0,0,J8/$J$105) -> 0.056403526 | L8: =K8-G8 -> 0.00020057791 | O8: =IF(ISNUMBER(M8),K8*M8,"") | P8: =E8/G8 -> 18539.953
A9: 4 | B9: ICICI Bank Ltd. | C9: ICICIBANK | D9: Banking | E9: 1441 | F9: 1030255 | G9: =F9/$F$105 -> 0.061190717 | H9: =$C$2*G9 -> 2325247.2 | I9: =ROUNDDOWN(H9/E9,0) -> 1613 | J9: =I9*E9 -> 2324333 | K9: =IF($J$105=0,0,J9/$J$105) -> 0.061403754 | L9: =K9-G9 -> 0.00021303709 | O9: =IF(ISNUMBER(M9),K9*M9,"") | P9: =E9/G9 -> 23549.324
A10: 5 | B10: Tata Consultancy Services Ltd. | C10: TCS | D10: IT | E10: 2324.2 | F10: 844253 | G10: =F10/$F$105 -> 0.050143359 | H10: =$C$2*G10 -> 1905447.6 | I10: =ROUNDDOWN(H10/E10,0) -> 819 | J10: =I10*E10 -> 1903519.8 | K10: =IF($J$105=0,0,J10/$J$105) -> 0.050286797 | L10: =K10-G10 -> 0.00014343792 | O10: =IF(ISNUMBER(M10),K10*M10,"") | P10: =E10/G10 -> 46351.103
A11: 6 | B11: Larsen & Toubro Limited | C11: LT | D11: Capital Goods & Defence | E11: 4006 | F11: 549301 | G11: =F11/$F$105 -> 0.032625051 | H11: =$C$2*G11 -> 1239751.9 | I11: =ROUNDDOWN(H11/E11,0) -> 309 | J11: =I11*E11 -> 1237854 | K11: =IF($J$105=0,0,J11/$J$105) -> 0.032701374 | L11: =K11-G11 -> 7.6322833e-05 | O11: =IF(ISNUMBER(M11),K11*M11,"") | P11: =E11/G11 -> 122789.08
A12: 7 | B12: Infosys Ltd | C12: INFY | D12: IT | E12: 1122.9 | F12: 459209 | G12: =F12/$F$105 -> 0.027274149 | H12: =$C$2*G12 -> 1036417.6 | I12: =ROUNDDOWN(H12/E12,0) -> 922 | J12: =I12*E12 -> 1035313.8 | K12: =IF($J$105=0,0,J12/$J$105) -> 0.027350708 | L12: =K12-G12 -> 7.6559749e-05 | O12: =IF(ISNUMBER(M12),K12*M12,"") | P12: =E12/G12 -> 41170.854
A13: 8 | B13: Hindustan Unilever Ltd. | C13: HINDUNILVR | D13: FMCG | E13: 2005 | F13: 461131 | G13: =F13/$F$105 -> 0.027388303 | H13: =$C$2*G13 -> 1040755.5 | I13: =ROUNDDOWN(H13/E13,0) -> 519 | J13: =I13*E13 -> 1040595 | K13: =IF($J$105=0,0,J13/$J$105) -> 0.027490226 | L13: =K13-G13 -> 0.00010192261 | O13: =IF(ISNUMBER(M13),K13*M13,"") | P13: =E13/G13 -> 73206.433
A14: 9 | B14: Sun Pharmaceutical Industries Ltd. | C14: SUNPHARMA | D14: Pharma & Healthcare | E14: 1919.7 | F14: 459857 | G14: =F14/$F$105 -> 0.027312636 | H14: =$C$2*G14 -> 1037880.2 | I14: =ROUNDDOWN(H14/E14,0) -> 540 | J14: =I14*E14 -> 1036638 | K14: =IF($J$105=0,0,J14/$J$105) -> 0.027385691 | L14: =K14-G14 -> 7.3055038e-05 | O14: =IF(ISNUMBER(M14),K14*M14,"") | P14: =E14/G14 -> 70286.15
A15: 10 | B15: Mahindra & Mahindra Ltd. | C15: M&M | D15: Automobile | E15: 3353 | F15: 392769 | G15: =F15/$F$105 -> 0.023328027 | H15: =$C$2*G15 -> 886465.03 | I15: =ROUNDDOWN(H15/E15,0) -> 264 | J15: =I15*E15 -> 885192 | K15: =IF($J$105=0,0,J15/$J$105) -> 0.023384821 | L15: =K15-G15 -> 5.6794059e-05 | O15: =IF(ISNUMBER(M15),K15*M15,"") | P15: =E15/G15 -> 143732.69
A16: 11 | B16: AXIS Bank Ltd. | C16: AXISBANK | D16: Banking | E16: 1261.8 | F16: 396207 | G16: =F16/$F$105 -> 0.023532223 | H16: =$C$2*G16 -> 894224.47 | I16: =ROUNDDOWN(H16/E16,0) -> 708 | J16: =I16*E16 -> 893354.4 | K16: =IF($J$105=0,0,J16/$J$105) -> 0.023600454 | L16: =K16-G16 -> 6.8230931e-05 | O16: =IF(ISNUMBER(M16),K16*M16,"") | P16: =E16/G16 -> 53620.094
A17: 12 | B17: ITC Ltd | C17: ITC | D17: FMCG | E17: 264.95 | F17: 330285 | G17: =F17/$F$105 -> 0.019616868 | H17: =$C$2*G17 -> 745440.97 | I17: =ROUNDDOWN(H17/E17,0) -> 2813 | J17: =I17*E17 -> 745304.35 | K17: =IF($J$105=0,0,J17/$J$105) -> 0.019689298 | L17: =K17-G17 -> 7.2430341e-05 | O17: =IF(ISNUMBER(M17),K17*M17,"") | P17: =E17/G17 -> 13506.234
A18: 13 | B18: Adani Ports and Special Economic Zone Ltd | C18: ADANIPORTS | D18: Ports & Services | E18: 1656.8 | F18: 393055 | G18: =F18/$F$105 -> 0.023345014 | H18: =$C$2*G18 -> 887110.53 | I18: =ROUNDDOWN(H18/E18,0) -> 535 | J18: =I18*E18 -> 886388 | K18: =IF($J$105=0,0,J18/$J$105) -> 0.023416417 | L18: =K18-G18 -> 7.1403127e-05 | O18: =IF(ISNUMBER(M18),K18*M18,"") | P18: =E18/G18 -> 70970.187
... A104: 99 | B104: SBI Funds Management Ltd | C104: SBIFUNDS | D104: Capital Markets | E104: 531.15 | F104: 108186.12 | G104: =F104/$F$105 -> 0.0064255803 | H104: =$C$2*G104 -> 244172.05 | I104: =ROUNDDOWN(H104/E104,0) -> 459 | J104: =I104*E104 -> 243797.85 | K104: =IF($J$105=0,0,J104/$J$105) -> 0.0064406018 | L104: =K104-G104 -> 1.5021448e-05 | O104: =IF(ISNUMBER(M104),K104*M104,"") | P104: =E104/G104 -> 82661.795
B105: TOTAL | F105: =SUM(F6:F104) -> 16836786 | G105: =SUM(G6:G104) -> 1 | H105: =SUM(H6:H104) -> 38000000 | I105: =SUM(I6:I104) -> 45260 | J105: =SUM(J6:J104) -> 37853272 | K105: =SUM(K6:K104) -> 1 | O105: =SUM(O6:O104) -> 0
